LICENSE
MANIFEST.in
README.rst
setup.cfg
setup.py
emailsms/__init__.py
emailsms.egg-info/PKG-INFO
emailsms.egg-info/SOURCES.txt
emailsms.egg-info/dependency_links.txt
emailsms.egg-info/top_level.txt