Metadata-Version: 1.1
Name: emailsms
Version: 0.1
Summary: Send text messages using email SMS gateways.
Home-page: https://bitbucket.org/socos_me/emailsms
Author: Brandon Istenes
Author-email: bistenes@socos.me
License: Apache License 2.0
Download-URL: https://bitbucket.org/socos_me/emailsms/get/0.1.tar.gz
Keywords: sms,texting,phone,gateway,email
Platform: UNKNOWN
Classifier: Development Status :: 4 - Beta
Classifier: License :: OSI Approved :: Apache Software License
